LICENSE
README.md
setup.py
disdata/__init__.py
disdata/constants.py
disdata/database.py
disdata/errors.py
disdata.egg-info/PKG-INFO
disdata.egg-info/SOURCES.txt
disdata.egg-info/dependency_links.txt
disdata.egg-info/requires.txt
disdata.egg-info/top_level.txt