Metadata-Version: 2.1
Name: disdata
Version: 0.0.2
Summary: A atabase for discord bots coded in disnake - easy to set up, maintain and interact with
Home-page: https://github.com/CaedenPH/disdata
Author: Caeden
License: MIT
Download-URL: https://github.com/CaedenPH/disdata/archive/refs/tags/v_0.0.2.tar.gz
Project-URL: Code, https://github.com/CaedenPH/disdata
Keywords: discord
Platform: UNKNOWN
Classifier: Development Status :: 5 - Production/Stable
Classifier: Framework :: AsyncIO
Classifier: Intended Audience :: Developers
Classifier: License :: OSI Approved :: MIT License
Classifier: Natural Language :: English
Classifier: Operating System :: OS Independent
Classifier: Programming Language :: Python :: 3 :: Only
Classifier: Programming Language :: Python :: 3.8
Classifier: Programming Language :: Python :: 3.9
Classifier: Topic :: Communications :: Chat
Classifier: Topic :: Internet
Classifier: Topic :: Utilities
Requires-Python: >=3.8.0
License-File: LICENSE
